README.md
setup.py
pynello/__init__.py
pynello/__main__.py
pynello.egg-info/PKG-INFO
pynello.egg-info/SOURCES.txt
pynello.egg-info/dependency_links.txt
pynello.egg-info/entry_points.txt
pynello.egg-info/requires.txt
pynello.egg-info/top_level.txt
pynello/private/__init__.py
pynello/private/exceptions.py
pynello/private/nello.py
pynello/private/utils.py
pynello/public/__init__.py
pynello/public/nello.py
pynello/public/nelloapiclient.py