Metadata-Version: 2.1
Name: pynello
Version: 2.0.2
Summary: Python library for nello.io intercoms
Home-page: https://github.com/pschmitt/pynello
Author: Philipp Schmitt
Author-email: philipp@schmitt.co
License: GPL3
Platform: UNKNOWN
